django_attack_blocker/__init__.py
django_attack_blocker/apps.py
django_attack_blocker/core.py
django_attack_blocker/utils.py
django_attack_blocker-1.0.8.dist-info/licenses/LICENSE
django_attack_blocker-1.0.8.dist-info/METADATA
django_attack_blocker-1.0.8.dist-info/WHEEL
django_attack_blocker-1.0.8.dist-info/top_level.txt
django_attack_blocker-1.0.8.dist-info/RECORD
