Metadata-Version: 2.4
Name: django_attack_blocker
Version: 1.0.8
Summary: ML-based IP blocking system for Django
Home-page: https://github.com/benab04/django-attack-blocker
Author: Ben Abraham Biju
Author-email: benabrahambiju@gmail.com
Classifier: Programming Language :: Python :: 3
Classifier: License :: OSI Approved :: MIT License
Classifier: Operating System :: OS Independent
Classifier: Framework :: Django
Classifier: Framework :: Django :: 3.2
Classifier: Framework :: Django :: 4.0
Classifier: Framework :: Django :: 4.1
Requires-Python: >=3.6
License-File: LICENSE
Requires-Dist: django>=3.2
Requires-Dist: pandas
Requires-Dist: numpy
Requires-Dist: scikit-learn
Requires-Dist: joblib
Dynamic: author
Dynamic: author-email
Dynamic: classifier
Dynamic: description
Dynamic: description-content-type
Dynamic: home-page
Dynamic: license-file
Dynamic: requires-dist
Dynamic: requires-python
Dynamic: summary
